{
	"Architecture": [
		"all"
	],
	"Binary": [
		"php-zend-stdlib"
	],
	"Build-Depends": [
		"debhelper (>= 9), phpab, pkg-php-tools (>= 1.7~)"
	],
	"Checksums-Sha256": [
		"9bc39e5d3043fea3649b12dd017f76fb78789ed27cdfe290fe5c2bb315df8a33 1649 php-zend-stdlib_3.0.1-1.dsc 7f980cbdfbbe7e5958066636ede19d9fc1c1cc71cee1ec97562e3d1f2630a1d6 29692 php-zend-stdlib_3.0.1.orig.tar.gz 46c00767ad43e0d0765acd311120ed84c7d86f77f32f2e6c5a2116f9b127713e 58096 php-zend-stdlib_3.0.1-1.debian.tar.xz"
	],
	"Directory": [
		"pool/main/p/php-zend-stdlib"
	],
	"Files": [
		"52a2abe10951f3de5b7699271a0395ac 1649 php-zend-stdlib_3.0.1-1.dsc 57292ed6552ee4f2726eb63a34a12647 29692 php-zend-stdlib_3.0.1.orig.tar.gz 38c105166b1d75c5fcdfd423f562aa53 58096 php-zend-stdlib_3.0.1-1.debian.tar.xz"
	],
	"Format": [
		"3.0 (quilt)"
	],
	"Homepage": [
		"http://framework.zend.com/"
	],
	"Maintainer": [
		"Debian PHP PEAR Maintainers <pkg-php-pear@lists.alioth.debian.org>"
	],
	"Package": [
		"php-zend-stdlib"
	],
	"Package-List": [
		"php-zend-stdlib deb php optional arch=all"
	],
	"Priority": [
		"extra"
	],
	"Section": [
		"misc"
	],
	"Standards-Version": [
		"3.9.8"
	],
	"Uploaders": [
		"David Prévot <taffit@debian.org>"
	],
	"Vcs-Browser": [
		"http://anonscm.debian.org/gitweb/?p=pkg-php/php-zend-stdlib.git"
	],
	"Vcs-Git": [
		"git://anonscm.debian.org/pkg-php/php-zend-stdlib.git"
	],
	"Version": [
		"3.0.1-1"
	]
}
