{
	"Architecture": [
		"any"
	],
	"Binary": [
		"postgresql-9.6-prefix"
	],
	"Build-Depends": [
		"debhelper (>= 7.0.50~), postgresql-server-dev-all (>= 158~)"
	],
	"Checksums-Sha256": [
		"0c466a35e61dc5b12f7c4eac56a14f1d5b41212c7d612646ad2def1f81a0330f 1991 prefix_1.2.5-1.dsc ffbdc9b945ebfd3a59d31b18116e920e51dc07002aae0b27fa28f9a6ce9ce9e0 75821 prefix_1.2.5.orig.tar.gz ff8b3c231c9a05e1b57d40aa20b070c4d74876c24a38fef12b36c0d0f59ed2c5 3600 prefix_1.2.5-1.debian.tar.xz"
	],
	"Directory": [
		"pool/main/p/prefix"
	],
	"Files": [
		"0be3d7e54d03cb4da69ea96378f2afef 1991 prefix_1.2.5-1.dsc b20398e5ba817f1151d26e4d2990bb20 75821 prefix_1.2.5.orig.tar.gz a7afe15ce2c932559175319fdbce63e2 3600 prefix_1.2.5-1.debian.tar.xz"
	],
	"Format": [
		"3.0 (quilt)"
	],
	"Maintainer": [
		"Debian PostgreSQL Maintainers <pkg-postgresql-public@lists.alioth.debian.org>"
	],
	"Package": [
		"prefix"
	],
	"Package-List": [
		"postgresql-9.6-prefix deb database extra arch=any"
	],
	"Priority": [
		"source"
	],
	"Section": [
		"misc"
	],
	"Standards-Version": [
		"3.9.6"
	],
	"Testsuite": [
		"autopkgtest"
	],
	"Testsuite-Triggers": [
		"make, postgresql-server-dev-all"
	],
	"Uploaders": [
		"Dimitri Fontaine <dim@tapoueh.org>, Christoph Berg <myon@debian.org>"
	],
	"Vcs-Browser": [
		"https://github.com/dimitri/prefix"
	],
	"Vcs-Git": [
		"git://github.com/dimitri/prefix.git"
	],
	"Version": [
		"1.2.5-1"
	]
}
