{
	"Architecture": [
		"all"
	],
	"Binary": [
		"coccinella"
	],
	"Build-Depends": [
		"debhelper (>= 7), quilt"
	],
	"Checksums-Sha1": [
		"78ccf11e171f9582520c2ad7f1b13198dfbe8350 1927 coccinella_0.96.20-7.dsc 19b94f3f7a055681f9366ec73d235b06c3101a3c 3483147 coccinella_0.96.20.orig.tar.gz 67b72f52a51a416686a1f571e0698b15a9ab77c1 8172 coccinella_0.96.20-7.debian.tar.xz"
	],
	"Checksums-Sha256": [
		"acb3c577bf1d7dff7eb236c38b433cdeb44d01f79e7e6c4192c7c3da0b6588ff 1927 coccinella_0.96.20-7.dsc 8ec4ca81d9cbad6cb643c3ef142d3429b2233f6e93dbf012deca916e61b2c184 3483147 coccinella_0.96.20.orig.tar.gz 5bf0f5d5eb8517acf04f018d457bd1f3a643f47610d103b337b4e09ac651ac1c 8172 coccinella_0.96.20-7.debian.tar.xz"
	],
	"Directory": [
		"pool/main/c/coccinella"
	],
	"Files": [
		"6c830bca0a6435204093a196c9ac283f 1927 coccinella_0.96.20-7.dsc 1e048333c6f7b9062d34f90ba2a30ea9 3483147 coccinella_0.96.20.orig.tar.gz 79213bb093411049fdd16e84aa26d584 8172 coccinella_0.96.20-7.debian.tar.xz"
	],
	"Format": [
		"3.0 (quilt)"
	],
	"Homepage": [
		"http://thecoccinella.org/"
	],
	"Maintainer": [
		"Mike Gabriel <sunweaver@debian.org>"
	],
	"Package": [
		"coccinella"
	],
	"Package-List": [
		"coccinella deb net extra"
	],
	"Priority": [
		"source"
	],
	"Section": [
		"net"
	],
	"Standards-Version": [
		"3.9.2"
	],
	"Uploaders": [
		"Miriam Ruiz <little_miry@yahoo.es>"
	],
	"Vcs-Browser": [
		"http://anonscm.debian.org/gitweb/?p=collab-maint/coccinella.git;a=summary"
	],
	"Vcs-Git": [
		"git://git.debian.org/collab-maint/coccinella.git"
	],
	"Version": [
		"0.96.20-7"
	]
}
