{
	"Architecture": [
		"any"
	],
	"Binary": [
		"libwn-dev, libwn6"
	],
	"Build-Depends": [
		"debmake (>= 3.7.2), c-shell"
	],
	"Directory": [
		"pool/main/libw/libwn6"
	],
	"Files": [
		"aa21ee0149d2f7caf11e82886addd466 724 libwn6_6.0-17.dsc 4967348565149ddadeaa797fc5be99bb 513471 libwn6_6.0.orig.tar.gz b01464d2c48b08a572dda6a5efe46752 48614 libwn6_6.0-17.diff.gz"
	],
	"Format": [
		"1.0"
	],
	"Maintainer": [
		"James R. Van Zandt <jrv@debian.org>"
	],
	"Package": [
		"libwn6"
	],
	"Priority": [
		"optional"
	],
	"Section": [
		"libs"
	],
	"Standards-Version": [
		"3.5.9"
	],
	"Version": [
		"6.0-17"
	]
}
