{
	"Architecture": [
		"any"
	],
	"Binary": [
		"minc-tools, libminc2-1, libminc-dev"
	],
	"Build-Depends": [
		"debhelper (>= 9), autotools-dev, dh-autoreconf, libnetcdf-dev, zlib1g-dev, texlive-latex-base, libhdf5-dev"
	],
	"Checksums-Sha1": [
		"0ee4202f7e097acf8ed6e48422187b8789a27eda 1490 minc_2.1.10-1.dsc 81c5693af303b46f2d83e1192429686829b13f62 1656060 minc_2.1.10.orig.tar.gz 1b13c18d7008f6c14f61634e464a3fa4fb4cd794 6507 minc_2.1.10-1.debian.tar.gz"
	],
	"Checksums-Sha256": [
		"439049a776fcd0a8b89756888d81920685207b1cf5547ff04bdc3109e7455123 1490 minc_2.1.10-1.dsc b9db9194b710aaea70425885a95d640f5c985a1baa9bd27f16bc7ff507b51228 1656060 minc_2.1.10.orig.tar.gz 38da404987c5bebae32456e24b10a281c26f28a776d2c25cf0e7873e26c79850 6507 minc_2.1.10-1.debian.tar.gz"
	],
	"Directory": [
		"pool/main/m/minc"
	],
	"Files": [
		"a4b57ff5f2af5e3ffbec8a4e3db7fa15 1490 minc_2.1.10-1.dsc 64032918928393ee6e1da7e8af3433d8 1656060 minc_2.1.10.orig.tar.gz 3700ab28b10be1c719a20909e2050aaf 6507 minc_2.1.10-1.debian.tar.gz"
	],
	"Format": [
		"3.0 (quilt)"
	],
	"Homepage": [
		"http://www.bic.mni.mcgill.ca/ServicesSoftware/HomePage"
	],
	"Maintainer": [
		"Debian Med Packaging Team <debian-med-packaging@lists.alioth.debian.org>"
	],
	"Package": [
		"minc"
	],
	"Package-List": [
		"libminc-dev deb libdevel optional libminc2-1 deb libs optional minc-tools deb science optional"
	],
	"Priority": [
		"source"
	],
	"Section": [
		"science"
	],
	"Standards-Version": [
		"3.9.2"
	],
	"Uploaders": [
		"Steve M. Robbins <smr@debian.org>"
	],
	"Vcs-Browser": [
		"http://svn.debian.org/wsvn/debian-med/trunk/packages/minc/trunk/?rev=0&sc=0"
	],
	"Vcs-Svn": [
		"svn://svn.debian.org/svn/debian-med/trunk/packages/minc/trunk/"
	],
	"Version": [
		"2.1.10-1"
	]
}
