{
	"Architecture": [
		"all"
	],
	"Binary": [
		"dlint"
	],
	"Build-Depends-Indep": [
		"debhelper (>= 3.0.5)"
	],
	"Directory": [
		"pool/main/d/dlint"
	],
	"Files": [
		"f72cb8ae374dc5ad960f7a7e0140d9bc 707 dlint_1.4.0-4.dsc 9fc692ab461af132a52a27a8dae1e07a 23007 dlint_1.4.0.orig.tar.gz 78926370e6aac417f526b12868595496 3753 dlint_1.4.0-4.diff.gz"
	],
	"Format": [
		"1.0"
	],
	"Maintainer": [
		"Florian Hinzmann <fh@debian.org>"
	],
	"Package": [
		"dlint"
	],
	"Priority": [
		"extra"
	],
	"Section": [
		"net"
	],
	"Standards-Version": [
		"3.5.6"
	],
	"Version": [
		"1.4.0-4"
	]
}
