{
	"Architecture": [
		"all"
	],
	"Binary": [
		"context-modules"
	],
	"Build-Depends": [
		"debhelper (>= 5.0.35)"
	],
	"Build-Depends-Indep": [
		"tex-common (>= 2.10)"
	],
	"Checksums-Sha1": [
		"26edb37678508b1bf160a5dfbf291603ddb8be08 1337 context-modules_20120611-1.dsc 8d00f6c2fb192b3c905860d725daa80d7362a5ab 11734374 context-modules_20120611.orig.tar.gz 33676001ca666e10f9bf1abe9e2a72d8dd2cc6f9 3533 context-modules_20120611-1.diff.gz"
	],
	"Checksums-Sha256": [
		"3290dc09375cbfa2d60c247c0d475fc52266780bbe397fd7b5d860e50007371f 1337 context-modules_20120611-1.dsc 706c8b0158a028348f80b4f22488f2340d7b3fb8019a8b1d2ef4c0a2256fad0d 11734374 context-modules_20120611.orig.tar.gz 5e912029be03b2ed9c26a476e3f2d432ddc566916d1d96687d226c487c09f2f8 3533 context-modules_20120611-1.diff.gz"
	],
	"Directory": [
		"pool/main/c/context-modules"
	],
	"Files": [
		"ec1ed26b9f63a1d76daa458026b8d92f 1337 context-modules_20120611-1.dsc dc1d08d740fb9f2cc2f8a4ad2afcff82 11734374 context-modules_20120611.orig.tar.gz 4f9b0d62772850ddfa2e1c33b8681194 3533 context-modules_20120611-1.diff.gz"
	],
	"Format": [
		"1.0"
	],
	"Maintainer": [
		"Debian TeX maintainers <debian-tex-maint@lists.debian.org>"
	],
	"Package": [
		"context-modules"
	],
	"Package-List": [
		"context-modules deb tex optional"
	],
	"Priority": [
		"source"
	],
	"Section": [
		"tex"
	],
	"Standards-Version": [
		"3.9.3"
	],
	"Uploaders": [
		"Norbert Preining <preining@debian.org>"
	],
	"Vcs-Browser": [
		"http://svn.debian.org/wsvn/debian-tex/context-modules/trunk/"
	],
	"Vcs-Svn": [
		"svn://svn.debian.org/svn/debian-tex/context-modules/trunk"
	],
	"Version": [
		"20120611-1"
	]
}
