{
	"Architecture": [
		"all"
	],
	"Binary": [
		"ruby-ms-rest-azure"
	],
	"Build-Depends": [
		"debhelper (>= 9~), gem2deb, ruby-concurrent (>= 1.0), ruby-faraday (>= 0.9), ruby-faraday-cookie-jar (>= 0.0.6), ruby-json (>= 1.7), ruby-ms-rest (>= 0.6.0)"
	],
	"Checksums-Sha256": [
		"0bbd1477872cca8c66b0949d827c7e9f60e9a8a470a2365ec61827d56d4f3fda 1870 ruby-ms-rest-azure_0.6.2-1.dsc a170ba70125778ec9c40e0cc05818fc88ff1f95a687adb8253cff68168330f12 11513 ruby-ms-rest-azure_0.6.2.orig.tar.gz 077b43fe453740b822d19682bf842d4d9bf3f009cf33e0bceddc5606d7a412dc 4456 ruby-ms-rest-azure_0.6.2-1.debian.tar.xz"
	],
	"Directory": [
		"pool/main/r/ruby-ms-rest-azure"
	],
	"Files": [
		"3f0414bdcf417eaadf0c2ea7a2cfdaa8 1870 ruby-ms-rest-azure_0.6.2-1.dsc 9680b3708e5c33bef7391e34b7559e57 11513 ruby-ms-rest-azure_0.6.2.orig.tar.gz ce71f741938463076fa468bbf2b5e23d 4456 ruby-ms-rest-azure_0.6.2-1.debian.tar.xz"
	],
	"Format": [
		"3.0 (quilt)"
	],
	"Homepage": [
		"https://github.com/Azure/autorest"
	],
	"Maintainer": [
		"Debian Azure Packaging Team <pkg-azure-team@lists.alioth.debian.org>"
	],
	"Package": [
		"ruby-ms-rest-azure"
	],
	"Package-List": [
		"ruby-ms-rest-azure deb ruby optional arch=all"
	],
	"Priority": [
		"extra"
	],
	"Ruby-Versions": [
		"all"
	],
	"Section": [
		"misc"
	],
	"Standards-Version": [
		"3.9.8"
	],
	"Testsuite": [
		"autopkgtest-pkg-ruby"
	],
	"Uploaders": [
		"Iain R. Learmonth <irl@debian.org>"
	],
	"Vcs-Browser": [
		"https://anonscm.debian.org/cgit/pkg-azure/ruby-ms-rest-azure.git"
	],
	"Vcs-Git": [
		"https://anonscm.debian.org/git/pkg-azure/ruby-ms-rest-azure.git"
	],
	"Version": [
		"0.6.2-1"
	]
}
