{
	"Architecture": [
		"all"
	],
	"Binary": [
		"shorewall-doc"
	],
	"Build-Depends-Indep": [
		"debhelper (>> 4.1.16)"
	],
	"Directory": [
		"pool/main/s/shorewall-doc"
	],
	"Files": [
		"e97fcb977cace2699d1be5967c28e6cc 576 shorewall-doc_2.2.3.dsc 0b9919637ad9ec8317e744f610416c2e 5938712 shorewall-doc_2.2.3.tar.gz"
	],
	"Format": [
		"1.0"
	],
	"Maintainer": [
		"Lorenzo Martignoni <lorenzo.martignoni@poste.it>"
	],
	"Package": [
		"shorewall-doc"
	],
	"Priority": [
		"optional"
	],
	"Section": [
		"net"
	],
	"Standards-Version": [
		"3.6.1"
	],
	"Uploaders": [
		"Matthias Klose <doko@debian.org>"
	],
	"Version": [
		"2.2.3"
	]
}
