{
	"Architecture": [
		"all"
	],
	"Binary": [
		"ca-certificates"
	],
	"Build-Depends-Indep": [
		"debhelper (>> 4.1.16), ruby"
	],
	"Directory": [
		"pool/main/c/ca-certificates"
	],
	"Files": [
		"a72937dce721edf8cb919a18aabce17e 547 ca-certificates_20061027~bpo.1.dsc 26d51627803eb7a52e577431c7c1cdb9 154174 ca-certificates_20061027~bpo.1.tar.gz"
	],
	"Format": [
		"1.0"
	],
	"Maintainer": [
		"Fumitoshi UKAI <ukai@debian.or.jp>"
	],
	"Package": [
		"ca-certificates"
	],
	"Priority": [
		"optional"
	],
	"Section": [
		"misc"
	],
	"Standards-Version": [
		"3.5.9"
	],
	"Version": [
		"20061027~bpo.1"
	]
}
