{
	"Architecture": [
		"any"
	],
	"Binary": [
		"rdfind"
	],
	"Build-Depends": [
		"debhelper (>= 7.0.50~), autotools-dev, nettle-dev"
	],
	"Checksums-Sha1": [
		"2461ed481c040d05381d6a8b120433eb58f5fa64 1839 rdfind_1.3.1-1.dsc c596e9e0d059e37135c9db62904426e37c879885 105343 rdfind_1.3.1.orig.tar.gz d36fb0b50fb7c0baf82f09e58bda5b0a6b09566b 1705 rdfind_1.3.1-1.debian.tar.gz"
	],
	"Checksums-Sha256": [
		"113b85d392d206880401c4333a8bd784efa2642b5b8618de97595b2dc21c87d1 1839 rdfind_1.3.1-1.dsc 9b09124858a54344810afe4f818cff5854b959ceaa4d47e66d0cb360928b3e10 105343 rdfind_1.3.1.orig.tar.gz 66e64b249eb8f9ebf9738aa22b664f7f18d29c18e9c9139fedef6e8b44f8d6a8 1705 rdfind_1.3.1-1.debian.tar.gz"
	],
	"Directory": [
		"pool/main/r/rdfind"
	],
	"Files": [
		"9ddd3bd9d43ac1cafd44e35794de6a09 1839 rdfind_1.3.1-1.dsc 72210a662ab7da623a699f62f891a0d2 105343 rdfind_1.3.1.orig.tar.gz 63307adddf70ed19f25eff740bbbd955 1705 rdfind_1.3.1-1.debian.tar.gz"
	],
	"Format": [
		"3.0 (quilt)"
	],
	"Homepage": [
		"http://rdfind.pauldreik.se/"
	],
	"Maintainer": [
		"TANIGUCHI Takaki <takaki@debian.org>"
	],
	"Package": [
		"rdfind"
	],
	"Package-List": [
		"rdfind deb utils extra"
	],
	"Priority": [
		"source"
	],
	"Section": [
		"utils"
	],
	"Standards-Version": [
		"3.9.3"
	],
	"Vcs-Browser": [
		"http://git.debian.org/?p=collab-maint/rdfind.git;a=summary"
	],
	"Vcs-Git": [
		"git://git.debian.org/collab-maint/rdfind.git"
	],
	"Version": [
		"1.3.1-1"
	]
}
