{
	"Architecture": [
		"any all"
	],
	"Binary": [
		"ruby-pg, libpgsql-ruby, libpgsql-ruby-doc, libpgsql-ruby1.8, libpgsql-ruby1.9.1"
	],
	"Build-Depends": [
		"debhelper (>= 7.0.50~), gem2deb (>= 0.3.0~), libpq-dev"
	],
	"Checksums-Sha1": [
		"0aa4e15dd662d229d42c858cbdb98c2a914ac0d7 1593 ruby-pg_0.13.2-2.dsc f5cb76b207e211fc24efa8bfbd4a572c0226aa5c 70403 ruby-pg_0.13.2.orig.tar.gz efa12cb7b8255514e84eb3b4fd718876b3b5d975 8185 ruby-pg_0.13.2-2.debian.tar.gz"
	],
	"Checksums-Sha256": [
		"04333bd7d40f1a285dc02ce9e5ea6efd2046eed6ebcf01b2ade123beff5e3d81 1593 ruby-pg_0.13.2-2.dsc 7d2f367ac874cfa49efa5484f0026dc1a3f6081f779e9d62003608f13be6bfd9 70403 ruby-pg_0.13.2.orig.tar.gz d8a3426096e9aa4c9c4c7f94e7df5132291165e87f406cb69b48ece58a95b481 8185 ruby-pg_0.13.2-2.debian.tar.gz"
	],
	"Directory": [
		"pool/main/r/ruby-pg"
	],
	"Dm-Upload-Allowed": [
		"yes"
	],
	"Files": [
		"39e55f1c2acfba7955368e4896ced8d2 1593 ruby-pg_0.13.2-2.dsc 9255e86a42bc67388501c01d65e01c79 70403 ruby-pg_0.13.2.orig.tar.gz 2a43e76c9d33f14358726087abaf4f85 8185 ruby-pg_0.13.2-2.debian.tar.gz"
	],
	"Format": [
		"3.0 (quilt)"
	],
	"Homepage": [
		"http://bitbucket.org/ged/ruby-pg"
	],
	"Maintainer": [
		"Debian Ruby Extras Maintainers <pkg-ruby-extras-maintainers@lists.alioth.debian.org>"
	],
	"Package": [
		"ruby-pg"
	],
	"Package-List": [
		"libpgsql-ruby deb oldlibs extra libpgsql-ruby-doc deb oldlibs extra libpgsql-ruby1.8 deb oldlibs extra libpgsql-ruby1.9.1 deb oldlibs extra ruby-pg deb ruby optional"
	],
	"Priority": [
		"source"
	],
	"Ruby-Versions": [
		"all"
	],
	"Section": [
		"ruby"
	],
	"Standards-Version": [
		"3.9.3"
	],
	"Uploaders": [
		"Dmitry Borodaenko <angdraug@debian.org>"
	],
	"Vcs-Browser": [
		"http://git.debian.org/?p=pkg-ruby-extras/ruby-pg.git;a=summary"
	],
	"Vcs-Git": [
		"git://git.debian.org/pkg-ruby-extras/ruby-pg.git"
	],
	"Version": [
		"0.13.2-2"
	]
}
