{
	"Architecture": [
		"any"
	],
	"Binary": [
		"filters"
	],
	"Build-Depends": [
		"debhelper (>= 7), flex, bison | byacc | btyacc, dpkg-dev (>= 1.9.0)"
	],
	"Checksums-Sha1": [
		"e9f34c5484beda71fb970f4d203c45c07a0e1cbe 814 filters_2.46.dsc 3b6cd2b47fc173d545b39201a6d399cc2a2e8836 51431 filters_2.46.tar.gz"
	],
	"Checksums-Sha256": [
		"cf978ce82525d5200e6abe3579b553b960dbffe81e260ba4d5d7cf447bad5fd1 814 filters_2.46.dsc 8cc469537992f8be566e973de856847f46da75b7efe10a1da36c9928968546dd 51431 filters_2.46.tar.gz"
	],
	"Directory": [
		"pool/main/f/filters"
	],
	"Files": [
		"245509daee0db301960874fd4326d301 814 filters_2.46.dsc 4eb1c6d80876b81f19b7b38012ec6e05 51431 filters_2.46.tar.gz"
	],
	"Format": [
		"1.0"
	],
	"Homepage": [
		"http://kitenet.net/~joey/code/filters/"
	],
	"Maintainer": [
		"Joey Hess <joeyh@debian.org>"
	],
	"Package": [
		"filters"
	],
	"Priority": [
		"optional"
	],
	"Section": [
		"games"
	],
	"Standards-Version": [
		"3.8.0"
	],
	"Vcs-Git": [
		"git://git.kitenet.net/filters"
	],
	"Version": [
		"2.46"
	]
}
