{
	"Architecture": [
		"all"
	],
	"Binary": [
		"cl-closer-mop"
	],
	"Build-Depends": [
		"debhelper (>= 4.0)"
	],
	"Build-Depends-Indep": [
		"dh-lisp"
	],
	"Directory": [
		"pool/main/c/cl-closer-mop"
	],
	"Files": [
		"9a5d0684534ebd90792efaab6b296d47 613 cl-closer-mop_0.4-1.dsc 653e0306f07275904ac054dd5ffe7410 22690 cl-closer-mop_0.4.orig.tar.gz 9c55899ff83c171f2f29d55d4e4da4d7 2549 cl-closer-mop_0.4-1.diff.gz"
	],
	"Format": [
		"1.0"
	],
	"Maintainer": [
		"Peter Van Eynde <pvaneynd@debian.org>"
	],
	"Package": [
		"cl-closer-mop"
	],
	"Priority": [
		"optional"
	],
	"Section": [
		"libs"
	],
	"Standards-Version": [
		"3.7.2.0"
	],
	"Version": [
		"1:0.4-1"
	]
}
