{
	"Architecture": [
		"any"
	],
	"Binary": [
		"miwm"
	],
	"Build-Depends": [
		"pkg-config, debhelper (>= 7.1), libx11-dev, libxpm-dev, x11proto-xext-dev, libxext-dev"
	],
	"Checksums-Sha1": [
		"718e3d04cf5d68c7ff86ee97910ff925d169655d 1164 miwm_1.1-1.dsc 8d2b606038c1542a6b45bc58a6ace8a701c10ee0 137560 miwm_1.1.orig.tar.gz d63e4a82855beeb53ccfea193b7a15bb7ffbb370 17146 miwm_1.1-1.debian.tar.gz"
	],
	"Checksums-Sha256": [
		"9fa41cec4466e36e37e687d850e48036cad4282813ad6c5e8bb6a55f6d5c2238 1164 miwm_1.1-1.dsc 24ec436046012f892cf51078a9518d9a9a2ce17929fcf5819dfbbc60764d3c5e 137560 miwm_1.1.orig.tar.gz a73cb9ba51af5d872329f206c0e9efbb98c67f1a11e24f2c8262438de23698a5 17146 miwm_1.1-1.debian.tar.gz"
	],
	"Directory": [
		"pool/main/m/miwm"
	],
	"Files": [
		"b97842f394e2fee5e0ff2abbfed674b0 1164 miwm_1.1-1.dsc 1779c27cc64b71a6348f94bf4fdbc323 137560 miwm_1.1.orig.tar.gz 4f22dcbfcb20fb1ed31d1594071da6cc 17146 miwm_1.1-1.debian.tar.gz"
	],
	"Format": [
		"3.0 (quilt)"
	],
	"Homepage": [
		"http://freshmeat.net/projects/miwm"
	],
	"Maintainer": [
		"Jari Aalto <jari.aalto@cante.net>"
	],
	"Package": [
		"miwm"
	],
	"Priority": [
		"optional"
	],
	"Section": [
		"x11"
	],
	"Standards-Version": [
		"3.8.3"
	],
	"Vcs-Browser": [
		"http://git.debian.org/?p=collab-maint/miwm.git"
	],
	"Vcs-Git": [
		"git://git.debian.org/git/collab-maint/miwm.git"
	],
	"Version": [
		"1.1-1"
	]
}
