{
	"Architecture": [
		"all"
	],
	"Binary": [
		"camlp4-doc"
	],
	"Directory": [
		"dists/potato/main/source/doc"
	],
	"Files": [
		"88f4c259f25a64464c24420de4e6a00d 834 camlp4-doc_2.04-2.dsc b52b7d83a07496730a3591903caae390 123964 camlp4-doc_2.04.orig.tar.gz 30c9f81339f517c57cf759f261218b96 2161 camlp4-doc_2.04-2.diff.gz"
	],
	"Maintainer": [
		"Fernando Sanchez <fer@debian.org>"
	],
	"Package": [
		"camlp4-doc"
	],
	"Priority": [
		"optional"
	],
	"Section": [
		"doc"
	],
	"Standards-Version": [
		"3.0.1"
	],
	"Version": [
		"2.04-2"
	]
}
