{
	"Architecture": [
		"any"
	],
	"Binary": [
		"ssh-askpass"
	],
	"Build-Depends": [
		"libx11-dev, libxt-dev, x-dev, xutils, debhelper"
	],
	"Directory": [
		"pool/main/s/ssh-askpass"
	],
	"Files": [
		"431e92eeb6b6bac0e5919dbd449b9170 614 ssh-askpass_1.2.4.1-6.1.dsc 8f2e41f3f7eaa8543a2440454637f3c3 29229 ssh-askpass_1.2.4.1.orig.tar.gz 4f6c0d269198f6f02023ab3f4a21e292 16366 ssh-askpass_1.2.4.1-6.1.diff.gz"
	],
	"Format": [
		"1.0"
	],
	"Maintainer": [
		"Philip Hands <phil@hands.com>"
	],
	"Package": [
		"ssh-askpass"
	],
	"Priority": [
		"optional"
	],
	"Section": [
		"net"
	],
	"Standards-Version": [
		"3.7.0.0"
	],
	"Version": [
		"1:1.2.4.1-6.1"
	]
}
