{
	"Architecture": [
		"any"
	],
	"Binary": [
		"xtell"
	],
	"Build-Depends": [
		"libreadline4-dev, libident-dev, debhelper (>= 4.1.16)"
	],
	"Directory": [
		"pool/main/x/xtell"
	],
	"Files": [
		"f54b160820adc6b03022211f6ca2b82b 545 xtell_2.10.1-0.1.dsc bec87c7bb9ee6f72410b2e23bda1c6db 34350 xtell_2.10.1-0.1.tar.gz"
	],
	"Format": [
		"1.0"
	],
	"Maintainer": [
		"Radovan Garabík <garabik@kassiopeia.juls.savba.sk>"
	],
	"Package": [
		"xtell"
	],
	"Priority": [
		"optional"
	],
	"Section": [
		"net"
	],
	"Standards-Version": [
		"3.5.8"
	],
	"Version": [
		"2.10.1-0.1"
	]
}
