{
	"Architecture": [
		"any"
	],
	"Binary": [
		"camlidl-doc, camlidl"
	],
	"Build-Depends": [
		"debhelper (>> 3.0.0), cpp, binutils, ocaml (>= 3.04-3)"
	],
	"Directory": [
		"pool/main/c/camlidl"
	],
	"Files": [
		"4ce904874a02e3c91efe609a14453d39 651 camlidl_1.02-6.dsc 57d8ff4fa49666646419eb6b91db5d6e 358735 camlidl_1.02.orig.tar.gz eee5ab8e9cb9a5139ec63a12b2f09a9c 6280 camlidl_1.02-6.diff.gz"
	],
	"Format": [
		"1.0"
	],
	"Maintainer": [
		"Stefano Zacchiroli <zack@debian.org>"
	],
	"Package": [
		"camlidl"
	],
	"Priority": [
		"optional"
	],
	"Section": [
		"devel"
	],
	"Standards-Version": [
		"3.5.2"
	],
	"Version": [
		"1.02-6"
	]
}
