{
	"Architecture": [
		"all"
	],
	"Binary": [
		"ruby-capybara"
	],
	"Build-Depends": [
		"debhelper (>= 7.0.50~), gem2deb (>= 0.3.0~), ruby-nokogiri, ruby-mime-types, ruby-rack, ruby-rack-test, ruby-xpath, ruby-sinatra, ruby-rspec (>= 2.11), yard, cucumber, rake"
	],
	"Checksums-Sha1": [
		"b51a12c82e3eb19ba771efe6ce0abc4d13c53a3f 2209 ruby-capybara_2.2.1-1~bpo70+1.dsc 9ef5a4d453c7ac90d89ad118e471ad1025fd5767 94576 ruby-capybara_2.2.1.orig.tar.gz 804cb79d0fa49a2f654fa2c60744842e1e29f591 4551 ruby-capybara_2.2.1-1~bpo70+1.debian.tar.gz"
	],
	"Checksums-Sha256": [
		"c726fdca4a342350c3b590a774f139dd1ecf6c7720539049c03ec726cbf2541b 2209 ruby-capybara_2.2.1-1~bpo70+1.dsc 91dbf9efde0fc63408107bcbe45f54e648eb5601b915763731ead4efe884683a 94576 ruby-capybara_2.2.1.orig.tar.gz 1ba63cbab84b57ad4c6942fb4c7fcc988f39d8972c778e204d4c1a0b13485719 4551 ruby-capybara_2.2.1-1~bpo70+1.debian.tar.gz"
	],
	"Directory": [
		"pool/main/r/ruby-capybara"
	],
	"Files": [
		"05d397a7150aeb641d5c2d25767dae69 2209 ruby-capybara_2.2.1-1~bpo70+1.dsc 3465ddb0b7b8dd075e26fa40b159130a 94576 ruby-capybara_2.2.1.orig.tar.gz 7a6cc1aa528ec87976b74491147496e0 4551 ruby-capybara_2.2.1-1~bpo70+1.debian.tar.gz"
	],
	"Format": [
		"3.0 (quilt)"
	],
	"Homepage": [
		"https://github.com/jnicklas/capybara"
	],
	"Maintainer": [
		"Debian Ruby Extras Maintainers <pkg-ruby-extras-maintainers@lists.alioth.debian.org>"
	],
	"Package": [
		"ruby-capybara"
	],
	"Package-List": [
		"ruby-capybara deb ruby optional"
	],
	"Priority": [
		"optional"
	],
	"Ruby-Versions": [
		"ruby1.9.1"
	],
	"Section": [
		"misc"
	],
	"Standards-Version": [
		"3.9.5"
	],
	"Uploaders": [
		"Jérémy Bobbio <lunar@debian.org>"
	],
	"Vcs-Browser": [
		"http://anonscm.debian.org/gitweb/?p=pkg-ruby-extras/ruby-capybara.git"
	],
	"Vcs-Git": [
		"git://anonscm.debian.org/pkg-ruby-extras/ruby-capybara.git"
	],
	"Version": [
		"2.2.1-1~bpo70+1"
	]
}
