{
	"Architecture": [
		"any"
	],
	"Binary": [
		"maximus"
	],
	"Build-Depends": [
		"cdbs, debhelper (>= 5), autotools-dev, quilt, gnome-pkg-tools (>= 0.10), libglib2.0-dev (>= 2.15.5), libgtk2.0-dev (>= 2.10.0), libgconf2-dev (>= 2.16.0), libwnck-dev, libgnomeui-dev, libxtst-dev, libfakekey-dev, libunique-dev"
	],
	"Checksums-Sha1": [
		"61e790b92f78801fc00bc19a58ca8a08fddd6cac 1371 maximus_0.4.14-3.dsc 8cba767d32974c94050a87955c6659c64c78b817 314053 maximus_0.4.14.orig.tar.gz 607915d8d2d67119e08425276e08a4f1fc2c1d7b 4493 maximus_0.4.14-3.diff.gz"
	],
	"Checksums-Sha256": [
		"1fdd18e6de6af629b1521c3415829f8a33e24bb550acacbfcc223adf4d9f2297 1371 maximus_0.4.14-3.dsc 02b1f92374b19716a9511f0beb9b67e2f7dcb0b34839c0c9bc90b63432c82b92 314053 maximus_0.4.14.orig.tar.gz 60407183b96c0e0e4953d72acf7d168243d1364f7bd21512b36979d81f71b308 4493 maximus_0.4.14-3.diff.gz"
	],
	"Directory": [
		"pool/main/m/maximus"
	],
	"Files": [
		"539ea8a92755b3dae64ac80238d5d0ba 1371 maximus_0.4.14-3.dsc c7d4b8cf318c90616be5ad1b0c299495 314053 maximus_0.4.14.orig.tar.gz fc2a472e853b5c54eae7b1784964274e 4493 maximus_0.4.14-3.diff.gz"
	],
	"Format": [
		"1.0"
	],
	"Homepage": [
		"https://launchpad.net/maximus"
	],
	"Maintainer": [
		"Debian QA Group <packages@qa.debian.org>"
	],
	"Package": [
		"maximus"
	],
	"Package-List": [
		"maximus deb gnome optional"
	],
	"Priority": [
		"source"
	],
	"Section": [
		"gnome"
	],
	"Standards-Version": [
		"3.9.3"
	],
	"Vcs-Browser": [
		"http://git.debian.org/?p=users/agx/maximus.git;a=summary"
	],
	"Vcs-Git": [
		"git://git.debian.org/users/agx/maximus.git"
	],
	"Version": [
		"0.4.14-3"
	]
}
