{
	"Architecture": [
		"all"
	],
	"Binary": [
		"libcmd-ruby, libcmd-ruby1.8"
	],
	"Build-Depends": [
		"cdbs, debhelper (>= 4.0.0)"
	],
	"Build-Depends-Indep": [
		"ruby-pkg-tools (>= 0.8), ruby1.8"
	],
	"Directory": [
		"pool/main/libc/libcmd-ruby"
	],
	"Files": [
		"72731c7ff705555db95d7a3a93b1f757 751 libcmd-ruby_0.8.0-3.dsc 3f8081760bb6d17a7cb296274164bfd1 25214 libcmd-ruby_0.8.0.orig.tar.gz 980b260bbba8dd6c9af769d1eb5b4245 2163 libcmd-ruby_0.8.0-3.diff.gz"
	],
	"Format": [
		"1.0"
	],
	"Maintainer": [
		"Paul van Tilburg <paulvt@debian.org>"
	],
	"Package": [
		"libcmd-ruby"
	],
	"Priority": [
		"optional"
	],
	"Section": [
		"ruby"
	],
	"Standards-Version": [
		"3.7.2"
	],
	"Uploaders": [
		"Debian Ruby Extras Maintainers <pkg-ruby-extras-maintainers@lists.alioth.debian.org>"
	],
	"Version": [
		"0.8.0-3"
	]
}
