{
	"Architecture": [
		"all"
	],
	"Binary": [
		"libhtml-wikiconverter-perl"
	],
	"Build-Depends": [
		"quilt, debhelper (>= 7.2), perl (>= 5.6.0-16), libhtml-tree-perl (>= 3.18), libcss-perl, liburi-perl (>= 1.35), libhtml-parser-perl, libhtml-tagset-perl, libparams-validate-perl (>= 0.77), libclass-data-accessor-perl (>= 0.02), libtest-simple-perl, libtest-pod-perl (>= 1.14), libtest-pod-coverage-perl (>= 1.04)"
	],
	"Checksums-Sha1": [
		"dc4a471cb73a6070bcbed7b7fa6e767969ba1701 1780 libhtml-wikiconverter-perl_0.68-1.dsc 34cb8ab7f5375aa7836325f9388d6ffe63c475eb 43912 libhtml-wikiconverter-perl_0.68.orig.tar.gz 16a4db059cf6f381d81c79b8473803c84b487cce 5018 libhtml-wikiconverter-perl_0.68-1.diff.gz"
	],
	"Checksums-Sha256": [
		"4fafae24e4bc4f1987903a6f4af0c34c44c2f38ab10bcd0a0aac32c9bea1d799 1780 libhtml-wikiconverter-perl_0.68-1.dsc 02d4408d8698db18ca66ce9a947a331043f38ae77ce7188b35dfbacab9d8e8e2 43912 libhtml-wikiconverter-perl_0.68.orig.tar.gz fb42c49de607ef81a02dca6e6e11536465ec37252aaf9f48b669938519d1bf5b 5018 libhtml-wikiconverter-perl_0.68-1.diff.gz"
	],
	"Directory": [
		"pool/main/libh/libhtml-wikiconverter-perl"
	],
	"Files": [
		"d1755a6cc4e3b9b1032dd78c21e7d597 1780 libhtml-wikiconverter-perl_0.68-1.dsc e6d8b16c23b6f38c51d8585f3423aca9 43912 libhtml-wikiconverter-perl_0.68.orig.tar.gz 6d821b6024fedcfb2ba98e64a8c12ba6 5018 libhtml-wikiconverter-perl_0.68-1.diff.gz"
	],
	"Format": [
		"1.0"
	],
	"Homepage": [
		"http://diberri.dyndns.org/wikipedia/html2wiki/"
	],
	"Maintainer": [
		"Debian Perl Group <pkg-perl-maintainers@lists.alioth.debian.org>"
	],
	"Package": [
		"libhtml-wikiconverter-perl"
	],
	"Priority": [
		"optional"
	],
	"Section": [
		"perl"
	],
	"Standards-Version": [
		"3.8.1"
	],
	"Uploaders": [
		"Jonas Smedegaard <dr@jones.dk>,  Rene Mayorga <rmayorga@debian.org.sv>,  Krzysztof Krzyżaniak (eloy) <eloy@debian.org>"
	],
	"Vcs-Browser": [
		"http://svn.debian.org/wsvn/collab-maint/deb-maint/libhtml-wikiconverter-perl/trunk"
	],
	"Vcs-Svn": [
		"svn://svn.debian.org/collab-maint/deb-maint/libhtml-wikiconverter-perl/trunk"
	],
	"Version": [
		"0.68-1"
	]
}
