{
	"Architecture": [
		"all"
	],
	"Binary": [
		"libwww-cnic-perl"
	],
	"Build-Depends": [
		"debhelper (>= 7)"
	],
	"Build-Depends-Indep": [
		"perl, libcrypt-ssleay-perl, libwww-perl"
	],
	"Checksums-Sha1": [
		"3d7c64b59e5a7fe6dd0e9ca1a59cf3d7549b1478 2139 libwww-cnic-perl_0.38-1.dsc 6db08612ab4e9dbc2f3526e00ca4ec3d64ce8111 29460 libwww-cnic-perl_0.38.orig.tar.gz ec3b854cefde7df278987af4b423efe5addd656e 4108 libwww-cnic-perl_0.38-1.debian.tar.gz"
	],
	"Checksums-Sha256": [
		"9f53bd5325b59772d4536c7b9b46bffa5ed4ab5ef00f0b7bf868c6efe2dd14b8 2139 libwww-cnic-perl_0.38-1.dsc 1135f771a7a26fc783d19c0cb39d78d82bd49162ed2e482ef12954907bdf694f 29460 libwww-cnic-perl_0.38.orig.tar.gz 6684e100e4f62c3491c9141048ce40b4beec1cdb3964c8234cbc24e9610b1d43 4108 libwww-cnic-perl_0.38-1.debian.tar.gz"
	],
	"Directory": [
		"pool/main/libw/libwww-cnic-perl"
	],
	"Files": [
		"9ed730797dfdc3dafa7d5009b91dd232 2139 libwww-cnic-perl_0.38-1.dsc 005bdcc0f2834945f9ed01bac4bbc148 29460 libwww-cnic-perl_0.38.orig.tar.gz 8cdb2570f5426bc04dd54c9002ff9c41 4108 libwww-cnic-perl_0.38-1.debian.tar.gz"
	],
	"Format": [
		"3.0 (quilt)"
	],
	"Homepage": [
		"http://toolkit.centralnic.com/downloads"
	],
	"Maintainer": [
		"Debian Perl Group <pkg-perl-maintainers@lists.alioth.debian.org>"
	],
	"Package": [
		"libwww-cnic-perl"
	],
	"Priority": [
		"source"
	],
	"Section": [
		"perl"
	],
	"Standards-Version": [
		"3.9.2"
	],
	"Uploaders": [
		"Jonathan McDowell <noodles@earth.li>, Nathan Handler <nhandler@ubuntu.com>, Jonathan Yu <jawnsy@cpan.org>, Chris Butler <chrisb@debian.org>, gregor herrmann <gregoa@debian.org>"
	],
	"Vcs-Browser": [
		"http://svn.debian.org/viewsvn/pkg-perl/trunk/libwww-cnic-perl/"
	],
	"Vcs-Svn": [
		"svn://svn.debian.org/pkg-perl/trunk/libwww-cnic-perl/"
	],
	"Version": [
		"0.38-1"
	]
}
