{
	"Architecture": [
		"all"
	],
	"Binary": [
		"gnome-doc-tools"
	],
	"Build-Depends-Indep": [
		"debhelper (>= 2.0.0)"
	],
	"Directory": [
		"pool/main/g/gnome-doc-tools"
	],
	"Files": [
		"44e24c68d34709444ec1393d52292e19 593 gnome-doc-tools_1.0-6.1.dsc 37a9094579fb6c1ba8045f4800607cc6 35718 gnome-doc-tools_1.0.orig.tar.gz 4d7bd15252b2ff5ae84b89194f8b7299 11275 gnome-doc-tools_1.0-6.1.diff.gz"
	],
	"Format": [
		"1.0"
	],
	"Maintainer": [
		"Jules Bean <jules@debian.org>"
	],
	"Package": [
		"gnome-doc-tools"
	],
	"Priority": [
		"optional"
	],
	"Section": [
		"gnome"
	],
	"Standards-Version": [
		"3.5.2"
	],
	"Version": [
		"1.0-6.1"
	]
}
