{
	"Architecture": [
		"all"
	],
	"Binary": [
		"gnome-sudoku"
	],
	"Build-Depends": [
		"debhelper (>= 5.0.0), cdbs (>= 0.4.43), python-all-dev (>= 2.3.5-11)"
	],
	"Build-Depends-Indep": [
		"gconf2 (>= 2.10.1-6), python-gtk2 (>= 2.8.6-3), python-glade2 (>= 2.6.3-2), python-gnome2 (>= 2.10.0-4), python-gnome2-extras (>= 2.10.2-1), python-numeric (>= 24.2-1), intltool (>= 0.34.1-1), python-imaging (>= 1.1.5-4), docbook-to-man (>= 1:2.0.0-20), python-support (>= 0.3)"
	],
	"Directory": [
		"pool/main/g/gnome-sudoku"
	],
	"Files": [
		"744ad12d0ba22d8384ad99feb1dae4b8 998 gnome-sudoku_0.5.0-1.dsc dc512c8e47c210ac8eedad2b055f81f8 180218 gnome-sudoku_0.5.0.orig.tar.gz 0ff88ce0868aa303ed76926d219bd884 4257 gnome-sudoku_0.5.0-1.diff.gz"
	],
	"Format": [
		"1.0"
	],
	"Maintainer": [
		"Utnubu Team <utnubu-maintainers@lists.alioth.debian.org>"
	],
	"Package": [
		"gnome-sudoku"
	],
	"Priority": [
		"optional"
	],
	"Section": [
		"games"
	],
	"Standards-Version": [
		"3.7.2"
	],
	"Uploaders": [
		"Gustavo Franco <stratus@debian.org>"
	],
	"Version": [
		"0.5.0-1"
	]
}
