{
	"Architecture": [
		"any"
	],
	"Binary": [
		"gphoto2"
	],
	"Build-Conflicts": [
		"liblockdev1-dev"
	],
	"Build-Depends": [
		"debhelper (>> 3.0.0), libgphoto2-2-dev (>= 2.2.0-1), zlib1g-dev, libtool, libgpmg1-dev [i386 ia64 alpha amd64 armeb arm hppa m32r m68k mips mipsel powerpc ppc64 s390 s390x sh3 sh3eb sh4 sh4eb sparc], libjpeg62-dev, libexif-dev (>= 0.5.9), libcdk5-dev, libreadline5-dev | libreadline-dev, pkg-config, libncurses5-dev, libpopt-dev, type-handling (>= 0.2.1)"
	],
	"Directory": [
		"pool/main/g/gphoto2"
	],
	"Files": [
		"e1339e7e700c2e489af87dff6b09ed3a 932 gphoto2_2.2.0-3.dsc a5508c41492e66b14fbde56ea7c8c980 831730 gphoto2_2.2.0.orig.tar.gz 1684fbec87ba2ab346557a7cb708cb03 95534 gphoto2_2.2.0-3.diff.gz"
	],
	"Format": [
		"1.0"
	],
	"Maintainer": [
		"Frederic Peters <fpeters@debian.org>"
	],
	"Package": [
		"gphoto2"
	],
	"Priority": [
		"extra"
	],
	"Section": [
		"utils"
	],
	"Standards-Version": [
		"3.6.2"
	],
	"Version": [
		"2.2.0-3"
	]
}
