{
	"Architecture": [
		"any"
	],
	"Binary": [
		"gpr"
	],
	"Build-Depends": [
		"debhelper (>= 4.1.16), gettext, autotools-dev, libtool, libppd-dev (>= 0.10), libgtk2.0-dev (>= 2.6), libpopt-dev, zlib1g-dev"
	],
	"Directory": [
		"pool/main/g/gpr"
	],
	"Files": [
		"4b6b3f978184419b895519120a0f9055 591 gpr_0.12deb1.dsc f65bf80672d7b98833131e76ba4e6fe7 323353 gpr_0.12deb1.tar.gz"
	],
	"Format": [
		"1.0"
	],
	"Maintainer": [
		"A Mennucc1 <mennucc1@debian.org>"
	],
	"Package": [
		"gpr"
	],
	"Priority": [
		"optional"
	],
	"Section": [
		"gnome"
	],
	"Standards-Version": [
		"3.6.2.0"
	],
	"Version": [
		"0.12deb1"
	]
}
