{
	"Architecture": [
		"any all"
	],
	"Binary": [
		"ncl-ncarg, libncarg0, libncarg-dev, libncarg-bin, libncarg-data"
	],
	"Build-Depends": [
		"flex, bison, gfortran, zlib1g-dev, libbz2-dev, libxt-dev, libxaw7-dev, libxmu-headers, libcairo2-dev, libjpeg-dev, libpng12-dev, pkg-config, fontconfig, libfontconfig1-dev, libfreetype6-dev, libexpat1-dev, libpixman-1-dev, libcurl4-gnutls-dev | libcurl-dev, libgdal-dev, libnetcdf-dev, libnetcdff-dev, libudunits2-dev, libatlas-dev, liblapack-dev, libblas-dev, libatlas3-base, libgrib2c-dev, libsphere-dev, libhdf4-alt-dev, libhdfeos-dev, libgctp-dev, libhe5-hdfeos-dev, tcsh | csh | c-shell, debhelper (>= 9), libhdf5-serial-dev | libhdf5-dev, libproj-dev"
	],
	"Checksums-Sha1": [
		"e64154a31abc16c19399f8963523b2efeef59caf 2533 ncl_6.3.0-4~bpo8+1.dsc d092bc548012ba0971c834dafab1431289ca97f5 29261436 ncl_6.3.0.orig.tar.xz 0dcbc3c89dd1a4b1133f1260d6947f9fd7437c44 29656 ncl_6.3.0-4~bpo8+1.debian.tar.xz"
	],
	"Checksums-Sha256": [
		"ff51da42fca57598220e6beae2c285b54e5ab044f468848e2af249eaba2d47d7 2533 ncl_6.3.0-4~bpo8+1.dsc e22a3433e615ceb0afa3773d96198018151835e4a4932d093c1cce4b6b3b7616 29261436 ncl_6.3.0.orig.tar.xz 9821ad77893720768672ca2f3b790b7bfa86b5918d8dadc1c31d889c46208e9c 29656 ncl_6.3.0-4~bpo8+1.debian.tar.xz"
	],
	"Directory": [
		"pool/main/n/ncl"
	],
	"Files": [
		"34528e177c8a59a257e32dcd3506bb06 2533 ncl_6.3.0-4~bpo8+1.dsc 14e2fd524a5f2c2c790d709b1e7af123 29261436 ncl_6.3.0.orig.tar.xz baf3afd6cf672bc2d8144da8c6e2f5c8 29656 ncl_6.3.0-4~bpo8+1.debian.tar.xz"
	],
	"Format": [
		"3.0 (quilt)"
	],
	"Homepage": [
		"http://www.ncl.ucar.edu/"
	],
	"Maintainer": [
		"Alastair McKinstry <mckinstry@debian.org>"
	],
	"Package": [
		"ncl"
	],
	"Package-List": [
		"libncarg-bin deb science optional arch=any libncarg-data deb science optional arch=all libncarg-dev deb libdevel optional arch=any libncarg0 deb libs optional arch=any ncl-ncarg deb science optional arch=any"
	],
	"Priority": [
		"optional"
	],
	"Section": [
		"misc"
	],
	"Standards-Version": [
		"3.9.6"
	],
	"Vcs-Git": [
		"git://anonscm.debian.org/debian-science/packages/ncl.git"
	],
	"Version": [
		"6.3.0-4~bpo8+1"
	]
}
