{
	"Architecture": [
		"all"
	],
	"Binary": [
		"libfrontier-rpc-perl"
	],
	"Build-Depends-Indep": [
		"perl (>= 5.6.0-16), libxml-parser-perl, libwww-perl, debhelper (>= 3.0.18)"
	],
	"Directory": [
		"pool/main/libf/libfrontier-rpc-perl"
	],
	"Files": [
		"4ea5435b6454bb07490b57926e83a1fe 712 libfrontier-rpc-perl_0.06-3.dsc 887174c45f4fc09e43c5ed93b16ae890 13857 libfrontier-rpc-perl_0.06.orig.tar.gz 1a670a12f830cd86bf716f66878ee08e 1888 libfrontier-rpc-perl_0.06-3.diff.gz"
	],
	"Format": [
		"1.0"
	],
	"Maintainer": [
		"Christopher C. Chimelis <chris@debian.org>"
	],
	"Package": [
		"libfrontier-rpc-perl"
	],
	"Priority": [
		"optional"
	],
	"Section": [
		"interpreters"
	],
	"Standards-Version": [
		"3.5.6.0"
	],
	"Version": [
		"0.06-3"
	]
}
