{
	"Architecture": [
		"all"
	],
	"Binary": [
		"libnet-finger-perl"
	],
	"Build-Depends-Indep": [
		"debhelper (>> 4.1), perl (>> 5.8), cdbs"
	],
	"Directory": [
		"pool/main/libn/libnet-finger-perl"
	],
	"Files": [
		"8d8fbde1bcc4bd2d8477b5faa6166a21 630 libnet-finger-perl_1.06-4.dsc 8ce9754d68ec93b2de142b70324396cc 3511 libnet-finger-perl_1.06.orig.tar.gz 0c9f4d15b1539156de2a7f64aed19f67 1684 libnet-finger-perl_1.06-4.diff.gz"
	],
	"Format": [
		"1.0"
	],
	"Maintainer": [
		"Michael Ablassmeier <abi@grinser.de>"
	],
	"Package": [
		"libnet-finger-perl"
	],
	"Priority": [
		"extra"
	],
	"Section": [
		"perl"
	],
	"Standards-Version": [
		"3.6.1.1"
	],
	"Version": [
		"1.06-4"
	]
}
