{
	"Architecture": [
		"all"
	],
	"Binary": [
		"posixtestsuite"
	],
	"Build-Depends": [
		"debhelper (>= 5), quilt (>= 0.40)"
	],
	"Build-Depends-Indep": [
		"expect"
	],
	"Checksums-Sha1": [
		"c29726166d9272fb30d196d39b7d038de50922d9 1334 posixtestsuite_1.5.2-3.dsc 7fa215c8e5a53f58d324cef1997edfea52f3d678 1092856 posixtestsuite_1.5.2.orig.tar.gz 97cb89001e81f23f274db836ba4740c614b92f74 3759 posixtestsuite_1.5.2-3.diff.gz"
	],
	"Checksums-Sha256": [
		"b79e3e5c2add7e3391a118e72910de62a9242892e5ead2091bca40e7495ddfe1 1334 posixtestsuite_1.5.2-3.dsc 15a2185672127cba851d35ec9d538ff6148defdbb75f99c7e9c50aeba0f94757 1092856 posixtestsuite_1.5.2.orig.tar.gz 94dce27e5ff56dc8c9c70d2700d60b8616f89a18c649eb9fa90d930998ceb6e1 3759 posixtestsuite_1.5.2-3.diff.gz"
	],
	"Directory": [
		"pool/main/p/posixtestsuite"
	],
	"Files": [
		"e79fb946498d3de35aec4045b5a10af8 1334 posixtestsuite_1.5.2-3.dsc 9a8e6516585c886fddc257270061b59c 1092856 posixtestsuite_1.5.2.orig.tar.gz 953e1445cff9510ae18ef034a9c0d424 3759 posixtestsuite_1.5.2-3.diff.gz"
	],
	"Format": [
		"1.0"
	],
	"Homepage": [
		"http://posixtest.sourceforge.net/"
	],
	"Maintainer": [
		"GNU/kFreeBSD Maintainers <debian-bsd@lists.debian.org>"
	],
	"Package": [
		"posixtestsuite"
	],
	"Priority": [
		"optional"
	],
	"Section": [
		"devel"
	],
	"Standards-Version": [
		"3.8.0"
	],
	"Uploaders": [
		"Guillem Jover <guillem@debian.org>, Aurelien Jarno <aurel32@debian.org>"
	],
	"Vcs-Browser": [
		"http://svn.debian.org/viewsvn/glibc-bsd/trunk/posixtestsuite/"
	],
	"Vcs-Svn": [
		"svn://svn.debian.org/svn/glibc-bsd/trunk/posixtestsuite/"
	],
	"Version": [
		"1.5.2-3"
	]
}
