{
	"Architecture": [
		"any"
	],
	"Binary": [
		"slrn, slrnpull"
	],
	"Build-Depends": [
		"debhelper (>= 9), libslang2-dev, libuu-dev, exim4 | mail-transport-agent, libgnutls-openssl-dev, po-debconf, autoconf, libcanlock2-dev, autotools-dev, dpkg-dev (>= 1.16.0), chrpath, dh-autoreconf, inn2-inews"
	],
	"Checksums-Sha1": [
		"f2dc43b95c25f2a8be49877ba2be223d9d173ce4 1894 slrn_1.0.2-2.dsc f6b10dce71913a4fd02fb5585168944b727fa6db 1532224 slrn_1.0.2.orig.tar.gz bc0a269f39e1f962f1ff87de17ab1975225e0800 49740 slrn_1.0.2-2.debian.tar.xz"
	],
	"Checksums-Sha256": [
		"b2bdf10e42e07e23664a5a578d379d32fb6b1b7f8ae9bc040b7297c95dcf009c 1894 slrn_1.0.2-2.dsc 22ecf8e97e4d1f59c4bba3301e6474cf9989b31d757c9a60b6d60a05bfa8c6be 1532224 slrn_1.0.2.orig.tar.gz 610dc4af3127e333c7325829b1b94234c67c90bae40e03b18d7b8faf568a4cd8 49740 slrn_1.0.2-2.debian.tar.xz"
	],
	"Directory": [
		"pool/main/s/slrn"
	],
	"Files": [
		"a5b651f1e60c535b3abb0d605c2e28de 1894 slrn_1.0.2-2.dsc cd21aa0f5ec9c2ec1a26e5f1322f6422 1532224 slrn_1.0.2.orig.tar.gz fdca8cb2606e2e369573e35b73609563 49740 slrn_1.0.2-2.debian.tar.xz"
	],
	"Format": [
		"3.0 (quilt)"
	],
	"Homepage": [
		"http://slrn.sourceforge.net/"
	],
	"Maintainer": [
		"Moritz Muehlenhoff <jmm@debian.org>"
	],
	"Package": [
		"slrn"
	],
	"Package-List": [
		"slrn deb news optional arch=any slrnpull deb news optional arch=any"
	],
	"Priority": [
		"source"
	],
	"Section": [
		"news"
	],
	"Standards-Version": [
		"3.9.6"
	],
	"Version": [
		"1.0.2-2"
	]
}
