{
	"Architecture": [
		"any"
	],
	"Binary": [
		"pngcrush"
	],
	"Build-Depends": [
		"debhelper (>= 5) , quilt, docbook-to-man, libpng12-dev, zlib1g-dev"
	],
	"Directory": [
		"pool/main/p/pngcrush"
	],
	"Files": [
		"260e3aac8217093ab2a3578687804e8a 682 pngcrush_1.6.4-2~bpo.2.dsc d2ae5f909e5f0a9b18cbf236420f20b7 48572 pngcrush_1.6.4.orig.tar.gz 9a3c0597987e8837b27308b6e8fd5812 12029 pngcrush_1.6.4-2~bpo.2.diff.gz"
	],
	"Format": [
		"1.0"
	],
	"Maintainer": [
		"Kapil Hari Paranjape <kapil@imsc.res.in>"
	],
	"Package": [
		"pngcrush"
	],
	"Priority": [
		"optional"
	],
	"Section": [
		"graphics"
	],
	"Standards-Version": [
		"3.7.2"
	],
	"Uploaders": [
		"Nelson A. de Oliveira <naoliv@gmail.com>"
	],
	"Version": [
		"1.6.4-2~bpo.2"
	]
}
