{
	"Architecture": [
		"all"
	],
	"Binary": [
		"php-horde-stream-filter"
	],
	"Build-Depends": [
		"debhelper (>= 8.0.0), pkg-php-tools, pear-horde-channel"
	],
	"Checksums-Sha1": [
		"d2109d96ec20e49fe6a64255343df77eff3d8f62 2108 php-horde-stream-filter_2.0.2-4.dsc 147eecd58fc2d0d580c5f30fa549b117a9deefb1 13403 php-horde-stream-filter_2.0.2.orig.tar.gz d0388b86608aaa97d94cacb2927c4f243819fb49 2400 php-horde-stream-filter_2.0.2-4.debian.tar.xz"
	],
	"Checksums-Sha256": [
		"b5d27ab5f8a331ee1bde7280f604c4ef98775146245292c4cadd8af07bb50660 2108 php-horde-stream-filter_2.0.2-4.dsc e283338773704f21c2f95f1ac248c8ad3e0937746ce3e25993d95695532e9df2 13403 php-horde-stream-filter_2.0.2.orig.tar.gz 2aa3c45eb18a8ae6205e7c451a7dd636f0c1ea952c3ad0286c7d9cc5a5549538 2400 php-horde-stream-filter_2.0.2-4.debian.tar.xz"
	],
	"Directory": [
		"pool/main/p/php-horde-stream-filter"
	],
	"Files": [
		"7a62670c0b5346e05c732efc3aa923f2 2108 php-horde-stream-filter_2.0.2-4.dsc ae3bfce5ce7b44b79d2d454a3fbc7e15 13403 php-horde-stream-filter_2.0.2.orig.tar.gz b3d147b549c6c5f6b336c311181b4d6b 2400 php-horde-stream-filter_2.0.2-4.debian.tar.xz"
	],
	"Format": [
		"3.0 (quilt)"
	],
	"Homepage": [
		"http://www.horde.org/"
	],
	"Maintainer": [
		"Horde Maintainers <pkg-horde-hackers@lists.alioth.debian.org>"
	],
	"Package": [
		"php-horde-stream-filter"
	],
	"Package-List": [
		"php-horde-stream-filter deb php extra arch=all"
	],
	"Priority": [
		"source"
	],
	"Section": [
		"php"
	],
	"Standards-Version": [
		"3.9.5"
	],
	"Testsuite": [
		"autopkgtest"
	],
	"Uploaders": [
		"Mathieu Parent <sathieu@debian.org>"
	],
	"Vcs-Browser": [
		"http://anonscm.debian.org/cgit/pkg-horde/PEAR/php-horde-stream-filter.git"
	],
	"Vcs-Git": [
		"git://anonscm.debian.org/pkg-horde/PEAR/php-horde-stream-filter.git"
	],
	"Version": [
		"2.0.2-4"
	]
}
