{
	"Architecture": [
		"any"
	],
	"Binary": [
		"libclass-mop-perl"
	],
	"Build-Depends": [
		"debhelper (>= 7), perl (>= 5.8.0-7), libsub-name-perl, libtest-exception-perl, libtest-pod-perl, libtest-pod-coverage-perl, libalgorithm-c3-perl, libclass-c3-perl, libmro-compat-perl, libsub-identify-perl"
	],
	"Checksums-Sha1": [
		"7aa14b4cb0df6fb3002ed0462ce55bef3a233585 1580 libclass-mop-perl_0.63-1.dsc c7e74f415003e764b885528d477cc5d119de891e 139059 libclass-mop-perl_0.63.orig.tar.gz a807c79732164bfd617de672f93fbb7be60e68ca 3667 libclass-mop-perl_0.63-1.diff.gz"
	],
	"Checksums-Sha256": [
		"c7117aec12e2b8a31fc353254dcf72a231fd96b77ee6e9909f5759c39d4be19d 1580 libclass-mop-perl_0.63-1.dsc 200537e1615f03eb56e2ff784b9ca37db0df27b074810c7ee46694e33e16ca33 139059 libclass-mop-perl_0.63.orig.tar.gz b60ecaa6c103bbea280744b7bdd6a123621802c86bf5cd1d2c59ba53435302d9 3667 libclass-mop-perl_0.63-1.diff.gz"
	],
	"Directory": [
		"pool/main/libc/libclass-mop-perl"
	],
	"Files": [
		"6e05ad58d3b2663d0354b544c1e28167 1580 libclass-mop-perl_0.63-1.dsc d3b00b0f5b1ec34324b24528e5d26cb1 139059 libclass-mop-perl_0.63.orig.tar.gz 9ecc44a74bfe452ec83a04dad9d1605c 3667 libclass-mop-perl_0.63-1.diff.gz"
	],
	"Format": [
		"1.0"
	],
	"Homepage": [
		"http://search.cpan.org/dist/Class-MOP/"
	],
	"Maintainer": [
		"Debian Perl Group <pkg-perl-maintainers@lists.alioth.debian.org>"
	],
	"Package": [
		"libclass-mop-perl"
	],
	"Priority": [
		"optional"
	],
	"Section": [
		"perl"
	],
	"Standards-Version": [
		"3.8.0.1"
	],
	"Uploaders": [
		"Krzysztof Krzyżaniak (eloy) <eloy@debian.org>, Damyan Ivanov <dmn@debian.org>, Russ Allbery <rra@debian.org>, gregor herrmann <gregoa@debian.org>"
	],
	"Vcs-Browser": [
		"http://svn.debian.org/wsvn/pkg-perl/trunk/libclass-mop-perl/"
	],
	"Vcs-Svn": [
		"svn://svn.debian.org/pkg-perl/trunk/libclass-mop-perl/"
	],
	"Version": [
		"0.63-1"
	]
}
