{
	"Architecture": [
		"any"
	],
	"Binary": [
		"linuxdoc-tools, linuxdoc-tools-text, linuxdoc-tools-latex, linuxdoc-tools-info"
	],
	"Build-Depends": [
		"debhelper (>= 4), perl, flex, gawk | mawk, sp | opensp, texinfo, groff (>= 1.15.3.1), texlive-base-bin, texlive-latex-recommended, texlive-fonts-recommended"
	],
	"Checksums-Sha1": [
		"ae82bfb19eb64e72338fc126e01587dc0ba3264d 1171 linuxdoc-tools_0.9.56.dsc 57e34f3f09c2f25b4dca34dab83708602b9dda51 610443 linuxdoc-tools_0.9.56.tar.gz"
	],
	"Checksums-Sha256": [
		"712b5c0f8b09ccacdedb27c7708a3071d4ca91d4c21232f4ef4b11402fa11126 1171 linuxdoc-tools_0.9.56.dsc 3752e62a499c9e737f2e25f132e8910b89fcbf75b0c2307de72207c597c0e2d2 610443 linuxdoc-tools_0.9.56.tar.gz"
	],
	"Directory": [
		"pool/main/l/linuxdoc-tools"
	],
	"Files": [
		"380ed9a08acfe289f178c8128270b107 1171 linuxdoc-tools_0.9.56.dsc 1cfe10e279394731b65fdac4f72ff5eb 610443 linuxdoc-tools_0.9.56.tar.gz"
	],
	"Format": [
		"1.0"
	],
	"Maintainer": [
		"Debian XML/SGML Group <debian-xml-sgml-pkgs@lists.alioth.debian.org>"
	],
	"Package": [
		"linuxdoc-tools"
	],
	"Priority": [
		"optional"
	],
	"Section": [
		"text"
	],
	"Standards-Version": [
		"3.8.0"
	],
	"Uploaders": [
		"Agustin Martin Domingo <agmartin@debian.org>"
	],
	"Vcs-Browser": [
		"http://git.debian.org/?p=users/agmartin/linuxdoc-tools.git;a=summary"
	],
	"Vcs-Git": [
		"git://git.debian.org/git/users/agmartin/linuxdoc-tools.git"
	],
	"Version": [
		"0.9.56"
	]
}
